wyn_template_library/__init__.py
wyn_template_library/modules.py
wyn_template_library-0.1.1.dist-info/METADATA
wyn_template_library-0.1.1.dist-info/WHEEL
wyn_template_library-0.1.1.dist-info/RECORD
