Metadata-Version: 2.1
Name: wyn-template-library
Version: 0.1.1
Summary: This is a template python library.
Author: Yiqiao Yin
Author-email: eagle0504@gmail.com
Requires-Python: >=3.9,<4.0
Classifier: Programming Language :: Python :: 3
Classifier: Programming Language :: Python :: 3.9
Classifier: Programming Language :: Python :: 3.10
Classifier: Programming Language :: Python :: 3.11
Classifier: Programming Language :: Python :: 3.12
Requires-Dist: matplotlib (>=3.9.0,<4.0.0)
Requires-Dist: numpy (>=2.0.0,<3.0.0)
Requires-Dist: openai (>=1.35.3,<2.0.0)
Requires-Dist: pandas (>=2.2.2,<3.0.0)
